streamlit_quantity_text_input/__init__.py
streamlit_quantity_text_input/streamlit_quantity_text_input.py
streamlit_quantity_text_input-0.1.0a0.dist-info/LICENSE.txt
streamlit_quantity_text_input-0.1.0a0.dist-info/METADATA
streamlit_quantity_text_input-0.1.0a0.dist-info/WHEEL
streamlit_quantity_text_input-0.1.0a0.dist-info/top_level.txt
streamlit_quantity_text_input-0.1.0a0.dist-info/RECORD
