Metadata-Version: 2.1
Name: streamlit_quantity_text_input
Version: 0.1.0a0
Summary: Streamlit input field that uses the pint library for parsing quantities
Author-email: Holger Døssing <hldn@novonordisk.com>
Maintainer-email: "NN dept. 244" <244AKA@novonordisk.com>
License: Copyright (c) 2018 The Python Packaging Authority
Project-URL: Homepage, https://sc216.corp.novocorp.net/rba244/quantity_text_input
Project-URL: Bug Reports, https://sc216.corp.novocorp.net/rba244/quantity_text_input/issues
Keywords: streamlit,pint,quantity,input,conversion
Classifier: License :: OSI Approved :: MIT License
Classifier: Programming Language :: Python :: 3
Classifier: Programming Language :: Python :: 3.7
Classifier: Programming Language :: Python :: 3.8
Classifier: Programming Language :: Python :: 3.9
Classifier: Programming Language :: Python :: 3.10
Classifier: Programming Language :: Python :: 3.11
Classifier: Programming Language :: Python :: 3 :: Only
Requires-Python: >=3.7
License-File: LICENSE.txt
Requires-Dist: streamlit >=1.15
Requires-Dist: pint >=0.23
